.gitignore
MANIFEST.in
README.rst
setup.cfg
setup.py
docs/HISTORY.txt
docs/LICENSE.GPL
docs/LICENSE.txt
docs/MANUAL.txt
raptus/__init__.py
raptus.article.table.egg-info/PKG-INFO
raptus.article.table.egg-info/SOURCES.txt
raptus.article.table.egg-info/dependency_links.txt
raptus.article.table.egg-info/entry_points.txt
raptus.article.table.egg-info/namespace_packages.txt
raptus.article.table.egg-info/not-zip-safe
raptus.article.table.egg-info/requires.txt
raptus.article.table.egg-info/top_level.txt
raptus/article/__init__.py
raptus/article/table/__init__.py
raptus/article/table/adapters.py
raptus/article/table/config.py
raptus/article/table/configure.zcml
raptus/article/table/field.py
raptus/article/table/index.py
raptus/article/table/interfaces.py
raptus/article/table/permissions.zcml
raptus/article/table/setuphandlers.py
raptus/article/table/types.py
raptus/article/table/utils.py
raptus/article/table/validator.py
raptus/article/table/vocabulary.py
raptus/article/table/widget.py
raptus/article/table/browser/__init__.py
raptus/article/table/browser/configlet.pt
raptus/article/table/browser/configlet.py
raptus/article/table/browser/configure.zcml
raptus/article/table/browser/row_icon.gif
raptus/article/table/browser/table.pt
raptus/article/table/browser/table.py
raptus/article/table/browser/table_icon.gif
raptus/article/table/browser/tables.pt
raptus/article/table/browser/tables.py
raptus/article/table/browser/tables_full.gif
raptus/article/table/browser/tables_left.gif
raptus/article/table/browser/tables_right.gif
raptus/article/table/browser/view.pt
raptus/article/table/content/__init__.py
raptus/article/table/content/configure.zcml
raptus/article/table/content/row.py
raptus/article/table/content/table.py
raptus/article/table/i18n/raptus.article-de.mo
raptus/article/table/i18n/raptus.article-de.po
raptus/article/table/i18n/raptus.article-fr.mo
raptus/article/table/i18n/raptus.article-fr.po
raptus/article/table/i18n/raptus.article.pot
raptus/article/table/profiles/default/controlpanel.xml
raptus/article/table/profiles/default/cssregistry.xml
raptus/article/table/profiles/default/factorytool.xml
raptus/article/table/profiles/default/jsregistry.xml
raptus/article/table/profiles/default/metadata.xml
raptus/article/table/profiles/default/propertiestool.xml
raptus/article/table/profiles/default/raptus.article.table-catalog.txt
