Metadata-Version: 1.1
Name: raptus.article.table
Version: 2.0b14
Summary: Provides a table component for articles
Home-page: https://github.com/Raptus/raptus.article.table
Author: Raptus AG
Author-email: dev@raptus.com
License: GPL
Platform: UNKNOWN
Classifier: Programming Language :: Python
Classifier: Topic :: Software Development :: Libraries :: Python Modules
